lockix/__init__.py
lockix/cli.py
lockix/config.py
lockix/core.py
lockix-0.1.2.dist-info/METADATA
lockix-0.1.2.dist-info/WHEEL
lockix-0.1.2.dist-info/entry_points.txt
lockix-0.1.2.dist-info/top_level.txt
lockix-0.1.2.dist-info/RECORD
