Metadata-Version: 2.4
Name: lockix
Version: 0.1.2
Summary: A secure file encryption and decryption tool
Home-page: https://github.com/ishanoshada/Lockix
Author: Ishan Oshada
Author-email: ishan.kodithuwakku.official@gmail.com
Keywords: encryption,security,files,cryptography
Classifier: Development Status :: 3 - Alpha
Classifier: Intended Audience :: End Users/Desktop
Classifier: License :: OSI Approved :: MIT License
Classifier: Programming Language :: Python :: 3
Classifier: Programming Language :: Python :: 3.6
Classifier: Programming Language :: Python :: 3.7
Classifier: Programming Language :: Python :: 3.8
Classifier: Programming Language :: Python :: 3.9
Requires-Dist: colorama
Requires-Dist: cryptography
Dynamic: author
Dynamic: author-email
Dynamic: classifier
Dynamic: description
Dynamic: description-content-type
Dynamic: home-page
Dynamic: keywords
Dynamic: requires-dist
Dynamic: summary
